cloudbuild_validator/__init__.py
cloudbuild_validator/config.py
cloudbuild_validator/core.py
cloudbuild_validator/main.py
cloudbuild_validator/validators.py
cloudbuild_validator/data/cloudbuild-specifications.yaml
cloudbuild_validator-0.1.1.dist-info/METADATA
cloudbuild_validator-0.1.1.dist-info/WHEEL
cloudbuild_validator-0.1.1.dist-info/entry_points.txt
cloudbuild_validator-0.1.1.dist-info/licenses/LICENSE
cloudbuild_validator-0.1.1.dist-info/RECORD
