Metadata-Version: 2.3
Name: cloudbuild-validator
Version: 0.1.1
Summary: A robust and extensible tool for validating Google Cloud Build YAML configuration files against schema specifications and custom rules.
Author-email: Ali Masri <alimasri1991@gmail.com>
Requires-Python: >=3.10
Requires-Dist: loguru>=0.7.2
Requires-Dist: pydantic-settings>=2.6.1
Requires-Dist: pydantic>=2.9.2
Requires-Dist: yamale>=5.2.1
